{
  "project_info": {
    "project_number": "967178533903",
    "project_id": "veloplan-b41d0",
    "storage_bucket": "veloplan-b41d0.appspot.com"
  },
  "client": [
    {
      "client_info": {
        "mobilesdk_app_id": "1:967178533903:android:48258af0945f24bc32777a",
        "android_client_info": {
          "package_name": "com.example.veloplan"
        }
      },
      "oauth_client": [
        {
          "client_id": "967178533903-v9u1kuev8b7k65d4mals5cao6c9uabkh.apps.googleusercontent.com",
          "client_type": 3
        }
      ],
      "api_key": [
        {
          "current_key": "AIzaSyDSyA35aKPLg_wZ1teZneokZKCR4jFN7z0"
        }
      ],
      "services": {
        "appinvite_service": {
          "other_platform_oauth_client": [
            {
              "client_id": "967178533903-v9u1kuev8b7k65d4mals5cao6c9uabkh.apps.googleusercontent.com",
              "client_type": 3
            }
          ]
        }
      }
    }
  ],
  "configuration_version": "1"
}